memberpress_client/__init__.py
memberpress_client/admin.py
memberpress_client/apps.py
memberpress_client/client.py
memberpress_client/constants.py
memberpress_client/decorators.py
memberpress_client/events.py
memberpress_client/member.py
memberpress_client/memberpress.py
memberpress_client/membership.py
memberpress_client/models.py
memberpress_client/receivers.py
memberpress_client/subscription.py
memberpress_client/transaction.py
memberpress_client/urls.py
memberpress_client/utils.py
memberpress_client/api/__init__.py
memberpress_client/api/v1/__init__.py
memberpress_client/api/v1/urls.py
memberpress_client/api/v1/views.py
memberpress_client/config/__init__.py
memberpress_client/config/api_router.py
memberpress_client/config/wsgi.py
memberpress_client/migrations/0001_initial.py
memberpress_client/migrations/0002_auto_20221219_0316.py
memberpress_client/migrations/0003_alter_memberpresseventlog_id.py
memberpress_client/migrations/__init__.py
memberpress_client/settings/__init__.py
memberpress_client/settings/common.py
memberpress_client/settings/local.py
memberpress_client/settings/production.py
memberpress_client/tests/__init__.py
memberpress_client/tests/test_client.py
memberpress_client/tests/test_events.py
memberpress_client/tests/test_member_nosubscription.py
memberpress_client/tests/test_member_offline.py
memberpress_client/tests/test_member_online.py
django_memberpress_client-1.0.5.dist-info/LICENSE.txt
django_memberpress_client-1.0.5.dist-info/METADATA
django_memberpress_client-1.0.5.dist-info/WHEEL
django_memberpress_client-1.0.5.dist-info/entry_points.txt
django_memberpress_client-1.0.5.dist-info/top_level.txt
django_memberpress_client-1.0.5.dist-info/RECORD
