Metadata-Version: 2.1
Name: django-memberpress-client
Version: 1.0.5
Summary: A Django plugin to add Memberpress REST API and Webhook integrations.
Home-page: https://github.com/lpm0073/django-memberpress-client
Author: Lawrence McDaniel
Author-email: Lawrence McDaniel <lpm0073@gmail.com>
Project-URL: Homepage, https://github.com/lpm0073/django-memberpress-client
Project-URL: Bug Tracker, https://github.com/lpm0073/django-memberpress-client/issues
Project-URL: Repository, https://github.com/lpm0073/django-memberpress-client
Keywords: Python,Django,Wordpress,MemberPress,REST API
Classifier: Programming Language :: Python :: 3
Classifier: License :: OSI Approved :: MIT License
Classifier: Operating System :: OS Independent
Requires-Python: >=3.8
License-File: LICENSE.txt
Requires-Dist: Django <=3.3,>=3.2
Requires-Dist: validators
Requires-Dist: django-environ
Provides-Extra: local
Requires-Dist: pre-commit ; extra == 'local'
Requires-Dist: black ; extra == 'local'
Requires-Dist: flake8 ; extra == 'local'
Requires-Dist: ipython ; extra == 'local'
